{
    "outputs": [
        {
            "created_at": "2017-04-17T19:54:03.129734Z",
            "data": {
                "concepts": [
                    {
                        "app_id": null,
                        "id": "ai_pFMkdMDt",
                        "name": "toy",
                        "value": 0.97297585
                    },
                    {
                        "app_id": null,
                        "id": "ai_Xxjc3MhT",
                        "name": "transportation system",
                        "value": 0.95958835
                    },
                    {
                        "app_id": null,
                        "id": "ai_WTrlNkqM",
                        "name": "vehicle",
                        "value": 0.95790213
                    },
                    {
                        "app_id": null,
                        "id": "ai_Dm5GLXnB",
                        "name": "illustration",
                        "value": 0.9514985
                    },
                    {
                        "app_id": null,
                        "id": "ai_786Zr311",
                        "name": "no person",
                        "value": 0.9264883
                    },
                    {
                        "app_id": null,
                        "id": "ai_LplXDDZ2",
                        "name": "car",
                        "value": 0.9224256
                    },
                    {
                        "app_id": null,
                        "id": "ai_pWCpgbXq",
                        "name": "humor",
                        "value": 0.90966165
                    },
                    {
                        "app_id": null,
                        "id": "ai_62K34TR4",
                        "name": "technology",
                        "value": 0.9080113
                    },
                    {
                        "app_id": null,
                        "id": "ai_JP8T36Nq",
                        "name": "sketch",
                        "value": 0.900959
                    },
                    {
                        "app_id": null,
                        "id": "ai_V2F286Wn",
                        "name": "fun",
                        "value": 0.89332044
                    },
                    {
                        "app_id": null,
                        "id": "ai_n9zMj1ln",
                        "name": "robot",
                        "value": 0.89106524
                    },
                    {
                        "app_id": null,
                        "id": "ai_qcLd7fgc",
                        "name": "child",
                        "value": 0.8890444
                    },
                    {
                        "app_id": null,
                        "id": "ai_VRmbGVWh",
                        "name": "travel",
                        "value": 0.8823277
                    },
                    {
                        "app_id": null,
                        "id": "ai_9Dcdh0PK",
                        "name": "house",
                        "value": 0.8695079
                    },
                    {
                        "app_id": null,
                        "id": "ai_l8TKp2h5",
                        "name": "people",
                        "value": 0.8667901
                    },
                    {
                        "app_id": null,
                        "id": "ai_6lhccv44",
                        "name": "business",
                        "value": 0.8661219
                    },
                    {
                        "app_id": null,
                        "id": "ai_8rNgfppJ",
                        "name": "symbol",
                        "value": 0.86576915
                    },
                    {
                        "app_id": null,
                        "id": "ai_HLmqFqBf",
                        "name": "train",
                        "value": 0.85483634
                    },
                    {
                        "app_id": null,
                        "id": "ai_Kq5T0N87",
                        "name": "engine",
                        "value": 0.8436189
                    },
                    {
                        "app_id": null,
                        "id": "ai_dxSG2s86",
                        "name": "man",
                        "value": 0.8435844
                    }
                ]
            },
            "id": "fac6a3415dd249969c198783fe63bf78",
            "input": {
                "data": {
                    "image": {
                        "url": "https://s3.amazonaws.com/clarifai-api/img/prod/fd575814cd924ce384de96d58a0656a4/d9fddccaf1d24bb1a3e8402a45d87c4b.jpeg"
                    }
                },
                "id": "e4349133c1f24c9498295c32289e9ab9"
            },
            "model": {
                "app_id": null,
                "created_at": "2016-03-09T17:11:39.608845Z",
                "id": "aaa03c23b3724a16a56b629203edc62c",
                "model_version": {
                    "active_concept_count": 9171,
                    "created_at": "2016-07-13T01:19:12.147644Z",
                    "id": "aa9ca48295b37401f8af92ad1af0d91d",
                    "metrics_status": {
                        "code": 21302,
                        "description": "Model is not yet evaluated."
                    },
                    "multiclass_metrics": {},
                    "status": {
                        "code": 21100,
                        "description": "Model trained successfully"
                    }
                },
                "name": "general-v1.3",
                "output_info": {
                    "message": "Show output_info with: GET /models/{model_id}/output_info",
                    "type": "concept",
                    "type_ext": "concept"
                }
            },
            "status": {
                "code": 10000,
                "description": "Ok"
            }
        }
    ],
    "response_time": 3.0278799533843994,
    "status": {
        "code": 10000,
        "description": "Ok"
    }
}