{
    "outputs": [
        {
            "created_at": "2017-04-17T20:02:04.514248Z",
            "data": {
                "concepts": [
                    {
                        "app_id": null,
                        "id": "ai_786Zr311",
                        "name": "no person",
                        "value": 0.9909892
                    },
                    {
                        "app_id": null,
                        "id": "ai_2FHPKk9B",
                        "name": "winter",
                        "value": 0.9717835
                    },
                    {
                        "app_id": null,
                        "id": "ai_pFMkdMDt",
                        "name": "toy",
                        "value": 0.9536268
                    },
                    {
                        "app_id": null,
                        "id": "ai_mKzmkKDG",
                        "name": "Christmas",
                        "value": 0.9352807
                    },
                    {
                        "app_id": null,
                        "id": "ai_l09WQRHT",
                        "name": "snow",
                        "value": 0.9177215
                    },
                    {
                        "app_id": null,
                        "id": "ai_P2ktCFHk",
                        "name": "plastic",
                        "value": 0.904878
                    },
                    {
                        "app_id": null,
                        "id": "ai_SVshtN54",
                        "name": "one",
                        "value": 0.878611
                    },
                    {
                        "app_id": null,
                        "id": "ai_V2F286Wn",
                        "name": "fun",
                        "value": 0.8696412
                    },
                    {
                        "app_id": null,
                        "id": "ai_V1FjkFXr",
                        "name": "leisure",
                        "value": 0.86748385
                    },
                    {
                        "app_id": null,
                        "id": "ai_j09mzT6j",
                        "name": "family",
                        "value": 0.85565627
                    },
                    {
                        "app_id": null,
                        "id": "ai_Pf2b7clG",
                        "name": "indoors",
                        "value": 0.8419776
                    },
                    {
                        "app_id": null,
                        "id": "ai_VRmbGVWh",
                        "name": "travel",
                        "value": 0.8219986
                    },
                    {
                        "app_id": null,
                        "id": "ai_2gmKZLxp",
                        "name": "cold",
                        "value": 0.81911224
                    },
                    {
                        "app_id": null,
                        "id": "ai_L92T2QtK",
                        "name": "decoration",
                        "value": 0.8160404
                    },
                    {
                        "app_id": null,
                        "id": "ai_wmbvr5TG",
                        "name": "celebration",
                        "value": 0.8120589
                    },
                    {
                        "app_id": null,
                        "id": "ai_qcLd7fgc",
                        "name": "child",
                        "value": 0.8011255
                    },
                    {
                        "app_id": null,
                        "id": "ai_0JbWBDPd",
                        "name": "color",
                        "value": 0.7842075
                    },
                    {
                        "app_id": null,
                        "id": "ai_62K34TR4",
                        "name": "technology",
                        "value": 0.7655964
                    },
                    {
                        "app_id": null,
                        "id": "ai_cMfj16kJ",
                        "name": "design",
                        "value": 0.75464886
                    },
                    {
                        "app_id": null,
                        "id": "ai_dPSZc2sM",
                        "name": "lid",
                        "value": 0.7523881
                    }
                ]
            },
            "id": "ee91574807c44e2ba2042ef410831c5d",
            "input": {
                "data": {
                    "image": {
                        "url": "https://s3.amazonaws.com/clarifai-api/img/prod/fd575814cd924ce384de96d58a0656a4/dbb49ce3fee2475483d07eacc8d4178c.jpeg"
                    }
                },
                "id": "f0dc79c058904d82a696c4ba6721e2ec"
            },
            "model": {
                "app_id": null,
                "created_at": "2016-03-09T17:11:39.608845Z",
                "id": "aaa03c23b3724a16a56b629203edc62c",
                "model_version": {
                    "active_concept_count": 9171,
                    "created_at": "2016-07-13T01:19:12.147644Z",
                    "id": "aa9ca48295b37401f8af92ad1af0d91d",
                    "metrics_status": {
                        "code": 21302,
                        "description": "Model is not yet evaluated."
                    },
                    "multiclass_metrics": {},
                    "status": {
                        "code": 21100,
                        "description": "Model trained successfully"
                    }
                },
                "name": "general-v1.3",
                "output_info": {
                    "message": "Show output_info with: GET /models/{model_id}/output_info",
                    "type": "concept",
                    "type_ext": "concept"
                }
            },
            "status": {
                "code": 10000,
                "description": "Ok"
            }
        }
    ],
    "response_time": 2.9518649578094482,
    "status": {
        "code": 10000,
        "description": "Ok"
    }
}