{"categories":[{"name":"others_","score":0.16796875}],"adult":{"isAdultContent":false,"isRacyContent":false,"adultScore":0.0314696729183197,"racyScore":0.041998166590929031},"tags":[{"name":"tree","confidence":0.99197405576705933},{"name":"indoor","confidence":0.94657796621322632},{"name":"window","confidence":0.92619782686233521}],"description":{"tags":["indoor","window","table","sitting","desk","front","computer","large","black","food","laptop","top","keyboard","vase","cat","standing","clock","red","white","phone"],"captions":[{"text":"a vase sitting on a desk","confidence":0.3850802902682926}]},"requestId":"42927edc-9dd7-4f00-8b37-334a9e2af9ff","metadata":{"width":3264,"height":2448,"format":"Jpeg"},"faces":[],"color":{"dominantColorForeground":"Black","dominantColorBackground":"Grey","dominantColors":["Black","White","Grey"],"accentColor":"8EA823","isBWImg":false},"imageType":{"clipArtType":0,"lineDrawingType":0}}